sech3r.py
secher/__init__.py
secher/core.py
secher/extra.py
secher/style.py
sech3r-4.9.dist-info/LICENSE
sech3r-4.9.dist-info/METADATA
sech3r-4.9.dist-info/WHEEL
sech3r-4.9.dist-info/entry_points.txt
sech3r-4.9.dist-info/top_level.txt
sech3r-4.9.dist-info/RECORD
