Metadata-Version: 2.1
Name: sech3r
Version: 4.9
Summary: HTTP Security Header Checker
Home-page: https://github.com/naryal2580/sech3r
Author: Captain Nick Lucifer
Author-email: naryal2580@gmail.com
License: UNKNOWN
Download-URL: https://github.com/naryal2580/sech3r/tarball/master
Platform: UNKNOWN
Classifier: Programming Language :: Python :: 3
Classifier: Environment :: Console
Classifier: License :: OSI Approved :: MIT License
Classifier: Topic :: Security
Classifier: Operating System :: OS Independent
Requires-Python: >=3
Requires-Dist: docopt
Requires-Dist: stoyled
